<?xml version="1.0" encoding="utf-8"?>
<annotation><version>5.4.1</version><flags></flags><shapes><label>sling</label><points>[740.2, 10.9]</points><points>[772.4046920821114, 124.9266862170088]</points><group_id></group_id><description></description><shape_type>line</shape_type><flags></flags><mask></mask></shapes><shapes><label>sling</label><points>[740.3, 10.9]</points><points>[777.9765395894428, 148.68035190615836]</points><group_id></group_id><description></description><shape_type>line</shape_type><flags></flags><mask></mask></shapes><shapes><label>sling</label><points>[740.1, 10.8]</points><points>[687.067448680352, 143.25513196480938]</points><group_id></group_id><description></description><shape_type>line</shape_type><flags></flags><mask></mask></shapes><shapes><label>sling</label><points>[740.2, 10.8]</points><points>[689.1202346041056, 119.06158357771261]</points><group_id></group_id><description></description><shape_type>line</shape_type><flags></flags><mask></mask></shapes><shapes><label>box</label><points>[677.4658676637507, 119.81043581110058]</points><points>[675.9148090313416, 147.69044663592587]</points><points>[672.408711470366, 232.9038612700722]</points><points>[780.4879797630489, 237.93434907495023]</points><points>[789.3223139448112, 157.01766542925503]</points><points>[777.6353591891744, 124.0477239466938]</points><group_id></group_id><description></description><shape_type>polygon</shape_type><flags></flags><mask></mask></shapes><shapes><label>hook</label><points>[740.1, 10.8]</points><group_id></group_id><description></description><shape_type>point</shape_type><flags></flags><mask></mask></shapes><imagePath>..\frames_to_be_marked\frame_5800.png</imagePath><imageHeight>720</imageHeight><imageWidth>1280</imageWidth></annotation>