<?xml version="1.0" encoding="utf-8"?>
<annotation><version>5.4.1</version><flags></flags><shapes><label>sling</label><points>[763.9, 88.9]</points><points>[735.4545454545455, 193.54838709677418]</points><group_id></group_id><description></description><shape_type>line</shape_type><flags></flags><mask></mask></shapes><shapes><label>sling</label><points>[769.6, 91.6]</points><points>[825.7815442561206, 237.09981167608285]</points><group_id></group_id><description></description><shape_type>line</shape_type><flags></flags><mask></mask></shapes><shapes><label>sling</label><points>[767.4, 92.4]</points><points>[773.6158192090396, 277.5894538606403]</points><group_id></group_id><description></description><shape_type>line</shape_type><flags></flags><mask></mask></shapes><shapes><label>sling</label><points>[762.2, 89.1]</points><points>[676.4406779661017, 225.2354048964218]</points><group_id></group_id><description></description><shape_type>line</shape_type><flags></flags><mask></mask></shapes><shapes><label>box</label><points>[760.6349206349206, 380.1587301587302]</points><points>[822.8645412967445, 333.2243744955609]</points><points>[836.031746031746, 249.20634920634922]</points><points>[739.6384725170947, 196.46292456707982]</points><points>[663.4126984126984, 228.57142857142858]</points><points>[659.2534301856334, 317.1132633844498]</points><group_id></group_id><description></description><shape_type>polygon</shape_type><flags></flags><mask></mask></shapes><shapes><label>hook</label><points>[765.3, 87.9]</points><group_id></group_id><description></description><shape_type>point</shape_type><flags></flags><mask></mask></shapes><imagePath>..\frames_to_be_marked\frame_1720.png</imagePath><imageHeight>720</imageHeight><imageWidth>1280</imageWidth></annotation>